Metadata-Version: 2.1
Name: pyposer
Version: 0.1.3
Summary: Python Packeage Manager
Home-page: https://github.com/alysson3dev/pyposer
Author: Alisson Santos
Author-email: dev.alysson@gmail.com
License: UNKNOWN
Keywords: PYPOSER,PIP,PACKAGE,KEYWORDS
Platform: UNKNOWN
Classifier: Development Status :: 3 - Alpha
Classifier: Intended Audience :: Developers
Classifier: Topic :: Software Development :: Build Tools
Classifier: License :: OSI Approved :: MIT License
Classifier: Programming Language :: Python :: 3.4
Classifier: Programming Language :: Python :: 3.5
Classifier: Programming Language :: Python :: 3.6
Classifier: Programming Language :: Python :: 3.9
